{
    "enabled": false,
    "featured": true,
    "fees": 1,
    "identifier": "https://github.com/blinkhash/blinkhash-server",
    "logo": "",
    "addresses": {
        "address": "",
        "tAddress": "",
        "zAddress": ""
    },
    "coin": {
        "name": "Bitcoin",
        "symbol": "BTC",
        "algorithm": "sha256",
        "peerMagic": "f9beb4d9",
        "peerMagicTestnet": "0b110907",
        "hasGetInfo": false,
        "hashrateType": "hashes",
        "overwinter": false,
        "requireShielding": false,
        "rewardType": "coinbasevalue",
        "sapling": false,
        "segwit": true,
        "txfee": 0.0004,
        "mainnet": {
            "network": "btc",
            "bech32": "bc",
            "bip32": {
                "public": "0488B21E"
            },
            "pubKeyHash": "00",
            "scriptHash": "05"
        },
        "parameters": {
            "N": "",
            "K": "",
            "personalization": ""
        },
        "testnet": {
            "network": "btc",
            "bech32": "tb",
            "bip32": {
                "public": "043587CF"
            },
            "pubKeyHash": "6F",
            "scriptHash": "C4"
        }
    },
    "daemons": [
        {
            "host": "127.0.0.1",
            "port": 8332,
            "user": "",
            "password": ""
        }
    ],
    "rewards": {
        "rewardType": "",
        "founders": {
            "interval": 0,
            "reward": 0,
            "startHeight": 0,
            "endHeight": 0,
            "recipients": []
        },
        "secureNodes": {
            "interval": 0,
            "reward": 0,
            "startHeight": 0,
            "endHeight": 0,
            "recipients": []
        },
        "superNodes": {
            "interval": 0,
            "reward": 0,
            "startHeight": 0,
            "endHeight": 0,
            "recipients": []
        },
        "treasury": {
            "interval": 0,
            "reward": 0,
            "startHeight": 0,
            "endHeight": 0,
            "recipients": []
        }
    },
    "paymentProcessing": {
        "enabled": true,
        "checkInterval": 20,
        "operationInterval": 0,
        "paymentInterval": 7200,
        "shieldInterval": 0,
        "minimumPayment": 0.005,
        "daemon": {
            "host": "127.0.0.1",
            "port": 8332,
            "user": "",
            "password": ""
        }
    },
    "ports": {},
    "p2p": {
        "enabled": true,
        "host": "127.0.0.1",
        "port": 8333,
        "disableTransactions": true
    },
    "rewardRecipients": {}
}
